{
	"videos": [
		{
			"id": 1,
			"titulo": "O labirinto do Logcat",
			"capa": "https://caelum-online-public.s3.amazonaws.com/2802-react-praticando/img2.png",
			"link": "https://www.youtube.com/embed/ypvGqZGJBls"
		},
		{
			"id": 2,
			"titulo": "Um componente no espaço",
			"capa": "https://caelum-online-public.s3.amazonaws.com/2802-react-praticando/img1.png",
			"link": "https://www.youtube.com/embed/jK0uiQ1ZQQQ"
		},
		{
			"id": 3,
			"titulo": "O poderoso JavaScript",
			"capa": "https://caelum-online-public.s3.amazonaws.com/2802-react-praticando/img4.png",
			"link": "https://www.youtube.com/embed/N1BSG02z-Mw"
		},
		{
			"id": 4,
			"titulo": "Dart, o Caçador de Andróides",
			"capa": "https://caelum-online-public.s3.amazonaws.com/2802-react-praticando/img3.png",
			"link": "https://www.youtube.com/embed/LLmBWjF6F8M"
		},
		{
			"id": 5,
			"titulo": "O Gato Fujão",
			"capa": "https://th.bing.com/th/id/R.1c9386e585502b4935ed0504bc960827?rik=o8wyPvwWOg134Q&riu=http%3a%2f%2fres.freestockphotos.biz%2fpictures%2f17%2f17885-cat-close-up-pv.jpg&ehk=NYLFMUUou9OHjdrWLAU5nGF04VJ2W%2f%2f4FeJnUTysg6M%3d&risl=&pid=ImgRaw&r=0",
			"link": "https://www.youtube.com/embed/K8e0MBJadGo"
		}
	]
}
